microedit/__init__.py
microedit/classes.py
microedit/commands.py
microedit/constants.py
microedit/main.py
microedit-1.2.0.dist-info/METADATA
microedit-1.2.0.dist-info/WHEEL
microedit-1.2.0.dist-info/entry_points.txt
microedit-1.2.0.dist-info/licenses/LICENSE
microedit-1.2.0.dist-info/RECORD
