Metadata-Version: 2.4
Name: MicroEdit
Version: 1.2.0
Summary: A non-interactive file editor
License: Zlib
License-File: LICENSE
Author: Kokonico
Author-email: kokonico@duck.com
Requires-Python: >=3.10,<4.0
Classifier: License :: OSI Approved
Classifier: Programming Language :: Python :: 3
Classifier: Programming Language :: Python :: 3.10
Classifier: Programming Language :: Python :: 3.11
Classifier: Programming Language :: Python :: 3.12
Classifier: Programming Language :: Python :: 3.13
Classifier: Programming Language :: Python :: 3.14
Requires-Dist: objlog (==3.0.0)
